nimbo/__init__.py
nimbo/main.py
nimbo/ami/__init__.py
nimbo/ami/copy_images.py
nimbo/core/__init__.py
nimbo/core/click_extensions.py
nimbo/core/constants.py
nimbo/core/print.py
nimbo/core/utils.py
nimbo/core/cloud_provider/__init__.py
nimbo/core/cloud_provider/provider/__init__.py
nimbo/core/cloud_provider/provider/services/__init__.py
nimbo/core/cloud_provider/provider/services/instance.py
nimbo/core/cloud_provider/provider/services/permissions.py
nimbo/core/cloud_provider/provider/services/storage.py
nimbo/core/cloud_provider/provider/services/utils.py
nimbo/core/cloud_provider/provider_impl/__init__.py
nimbo/core/cloud_provider/provider_impl/aws/__init__.py
nimbo/core/cloud_provider/provider_impl/aws/aws_provider.py
nimbo/core/cloud_provider/provider_impl/aws/services/__init__.py
nimbo/core/cloud_provider/provider_impl/aws/services/aws_instance.py
nimbo/core/cloud_provider/provider_impl/aws/services/aws_permissions.py
nimbo/core/cloud_provider/provider_impl/aws/services/aws_storage.py
nimbo/core/cloud_provider/provider_impl/aws/services/aws_utils.py
nimbo/core/cloud_provider/provider_impl/gcp/__init__.py
nimbo/core/cloud_provider/provider_impl/gcp/gcp_provider.py
nimbo/core/cloud_provider/provider_impl/gcp/services/__init__.py
nimbo/core/cloud_provider/provider_impl/gcp/services/gcp_instance.py
nimbo/core/cloud_provider/provider_impl/gcp/services/gcp_permissions.py
nimbo/core/cloud_provider/provider_impl/gcp/services/gcp_storage.py
nimbo/core/cloud_provider/provider_impl/gcp/services/gcp_utils.py
nimbo/core/config/__init__.py
nimbo/core/config/aws_config.py
nimbo/core/config/common_config.py
nimbo/core/config/gcp_config.py
nimbo/core/config/yaml_loader.py
nimbo/scripts/remote_s3_test.sh
nimbo/scripts/remote_setup.sh
nimbo/tests/__init__.py
nimbo/tests/aws/__init__.py
nimbo/tests/aws/config.py
nimbo/tests/aws/test_cli.py
nimbo/tests/aws/test_core.py
nimbo/tests/aws/test_execute.py
nimbo/tests/aws/utils.py
nimbo-0.3.2.dist-info/LICENSE
nimbo-0.3.2.dist-info/METADATA
nimbo-0.3.2.dist-info/WHEEL
nimbo-0.3.2.dist-info/entry_points.txt
nimbo-0.3.2.dist-info/top_level.txt
nimbo-0.3.2.dist-info/RECORD
