Metadata-Version: 2.1
Name: nimbo
Version: 0.3.2
Summary: Run machine learning jobs on AWS with a single command.
Home-page: https://github.com/nimbo-sh/nimbo
Author: NimboSH, Ltd.
Author-email: support@nimbo.sh
License: UNKNOWN
Project-URL: Bug Tracker, https://github.com/nimbo-sh/nimbo/issues
Platform: UNKNOWN
Classifier: Development Status :: 3 - Alpha
Classifier: Operating System :: POSIX :: Linux
Classifier: Operating System :: Unix
Classifier: Operating System :: MacOS
Classifier: Programming Language :: Python :: 3
Requires-Python: >=3.6
License-File: LICENSE
Requires-Dist: colorama (==0.4.3)
Requires-Dist: requests (>=2.25)
Requires-Dist: click (>=7.0)
Requires-Dist: pydantic (>=1.7.0)
Requires-Dist: pyyaml (>=5.3.0)
Requires-Dist: boto3 (>=1.17)
Requires-Dist: awscli (>=1.19<2.0)
Requires-Dist: rich (>=10.1.0)
Requires-Dist: python-dateutil (>=2.8.0)
